strmath/__init__.py
strmath/enums.py
strmath/errors.py
strmath/evaluation.py
strmath/operators.py
strmath/tokenization.py
strmath/types.py
strmath-1.1.dist-info/LICENSE
strmath-1.1.dist-info/WHEEL
strmath-1.1.dist-info/METADATA
strmath-1.1.dist-info/RECORD
