Metadata-Version: 2.1
Name: strmath
Version: 1.1
Summary: A module for evaluating math expressions without eval()
Home-page: https://github.com/Exenifix/strmath
License: MIT
Keywords: math,parse,str
Author: Exenifix
Requires-Python: >=3.10,<4.0
Classifier: License :: OSI Approved :: MIT License
Classifier: Programming Language :: Python :: 3
Classifier: Programming Language :: Python :: 3.10
Project-URL: Repository, https://github.com/Exenifix/strmath
